setup.py
BUPTNetLogin.egg-info/PKG-INFO
BUPTNetLogin.egg-info/SOURCES.txt
BUPTNetLogin.egg-info/dependency_links.txt
BUPTNetLogin.egg-info/entry_points.txt
BUPTNetLogin.egg-info/requires.txt
BUPTNetLogin.egg-info/top_level.txt
app/__init__.py
app/bupt_net_login.py
app/line_option.py