Metadata-Version: 1.0
Name: BUPTNetLogin
Version: 0.1.0
Summary: Command line tool to login the BUPT net
Home-page: https://www.ingbyr.com
Author: ingbyr
Author-email: ingbyr@outlook.com
License: UNKNOWN
Platform: UNKNOWN
